diagho_toolkit/__init__.py
diagho_toolkit/fasta/__init__.py
diagho_toolkit/fasta/reader.py
diagho_toolkit/file/__init__.py
diagho_toolkit/file/db_file_path.py
diagho_toolkit/gff3/__init__.py
diagho_toolkit/gff3/reader.py
diagho_toolkit/gnomad_constraint/__init__.py
diagho_toolkit/gnomad_constraint/reader.py
diagho_toolkit/hgnc/__init__.py
diagho_toolkit/hgnc/reader.py
diagho_toolkit/hpo/__init__.py
diagho_toolkit/hpo/reader.py
diagho_toolkit/models/__init__.py
diagho_toolkit/models/clinvar.py
diagho_toolkit/models/feature.py
diagho_toolkit/models/gene.py
diagho_toolkit/models/gnomad.py
diagho_toolkit/models/gnomad_constraint.py
diagho_toolkit/models/pathology.py
diagho_toolkit/models/region.py
diagho_toolkit/models/sequence.py
diagho_toolkit/models/symptom.py
diagho_toolkit/models/variant.py
diagho_toolkit/omim/__init__.py
diagho_toolkit/omim/reader.py
diagho_toolkit/vcf/__init__.py
diagho_toolkit/vcf/example.py
diagho_toolkit/vcf/info_model.py
diagho_toolkit/vcf/reader.py
diagho_toolkit-0.1.1.dist-info/METADATA
diagho_toolkit-0.1.1.dist-info/WHEEL
diagho_toolkit-0.1.1.dist-info/top_level.txt
diagho_toolkit-0.1.1.dist-info/RECORD
