Metadata-Version: 2.1
Name: diagho_toolkit
Version: 0.1.1
Summary: Library with useful tools for processing genomic data
Author-email: Diagho Team <admin@diagho.com>
Project-URL: Homepage, https://github.com/DiaghoProject/python-diagho-toolkit
Project-URL: Bug Tracker, https://github.com/DiaghoProject/python-diagho-toolkit/issues
Classifier: Programming Language :: Python :: 3
Classifier: License :: OSI Approved :: MIT License
Classifier: Operating System :: OS Independent
Requires-Python: >=3.9
License-File: LICENSE
